notist/__init__.py
notist/_core.py
notist/_log.py
notist/_utils.py
notist/_watch.py
notist/_notifiers/__init__.py
notist/_notifiers/base.py
notist/_notifiers/discord.py
notist/_notifiers/slack.py
notist-0.1.0.dist-info/licenses/LICENSE
notist-0.1.0.dist-info/METADATA
notist-0.1.0.dist-info/WHEEL
notist-0.1.0.dist-info/top_level.txt
notist-0.1.0.dist-info/RECORD
