Metadata-Version: 2.4
Name: notist
Version: 0.1.0
Summary: A simple package to send notifications of script execution status.
Author-email: Kaito Baba <k.ai.to47802@gmail.com>
License: MIT License
Project-URL: Homepage, https://github.com/kaito47802/NotifyState
Keywords: notification,alert,slack,discord,messaging,bot,monitoring,automation,development,productivity,kaggle,data-science,machine-learning,deep-learning,ai,artificial-intelligence
Classifier: License :: OSI Approved :: MIT License
Classifier: Programming Language :: Python :: 3.9
Classifier: Programming Language :: Python :: 3.10
Classifier: Programming Language :: Python :: 3.11
Classifier: Programming Language :: Python :: 3.12
Classifier: Programming Language :: Python :: 3 :: Only
Classifier: Typing :: Typed
Classifier: Intended Audience :: Science/Research
Classifier: Intended Audience :: Developers
Classifier: Topic :: System :: Monitoring
Classifier: Topic :: System :: Logging
Classifier: Topic :: Communications :: Chat
Classifier: Topic :: Scientific/Engineering
Classifier: Topic :: Scientific/Engineering :: Artificial Intelligence
Classifier: Topic :: Software Development
Classifier: Topic :: Software Development :: Libraries
Classifier: Topic :: Software Development :: Libraries :: Python Modules
Requires-Python: >=3.9
License-File: LICENSE
Requires-Dist: slack_sdk>=3.33.1
Requires-Dist: requests>=2.28.1
Requires-Dist: typing-extensions
Provides-Extra: check
Requires-Dist: ruff; extra == "check"
Requires-Dist: mypy; extra == "check"
Requires-Dist: types-setuptools; extra == "check"
Requires-Dist: types-requests; extra == "check"
Provides-Extra: test
Requires-Dist: pytest; extra == "test"
Provides-Extra: docs
Requires-Dist: sphinx; extra == "docs"
Requires-Dist: sphinx-autodoc-typehints; extra == "docs"
Requires-Dist: pydata_sphinx_theme; extra == "docs"
Requires-Dist: sphinx-copybutton; extra == "docs"
Requires-Dist: sphinx-toolbox; extra == "docs"
Dynamic: license-file
